pds.registry-1.4.0-py3.9-nspkg.pth
pds/registry/VERSION.txt
pds/registry/__init__.py
pds/registry/tests/test_true.py
pds/registry/tests/__pycache__/test_true.cpython-39-pytest-7.4.4.pyc
pds/registry/utils/__init__.py
pds/registry/utils/geostac/__init__.py
pds/registry/utils/geostac/create_lola_pds4.py
pds/registry/utils/geostac/templates/__init__.py
pds/registry/utils/geostac/templates/product-browse-template.xml
pds/registry/utils/geostac/templates/product-external-template.xml
pds/registry/utils/treks/__init__.py
pds/registry/utils/treks/create_treks_pds4.py
pds/registry/utils/treks/product_collection_builder.py
pds/registry/utils/treks/product_service_builder.py
pds/registry/utils/treks/templates/__init__.py
pds/registry/utils/treks/templates/product-collection-template.xml
pds/registry/utils/treks/templates/product-service-template.xml
pds_registry-1.4.0.dist-info/licenses/LICENSE.md
pds_registry-1.4.0.dist-info/licenses/NOTICE.txt
pds_registry-1.4.0.dist-info/METADATA
pds_registry-1.4.0.dist-info/WHEEL
pds_registry-1.4.0.dist-info/entry_points.txt
pds_registry-1.4.0.dist-info/namespace_packages.txt
pds_registry-1.4.0.dist-info/top_level.txt
pds_registry-1.4.0.dist-info/zip-safe
pds_registry-1.4.0.dist-info/RECORD
