Metadata-Version: 2.4
Name: pds.registry
Version: 1.4.0
Summary: PDS Registry is a service and application for tracking, searching, auditing, locating, and managing artifacts within the system—data and label files, schemas, dictionaries, services, and more.
Home-page: https://github.com/NASA-PDS/registry
Download-URL: https://github.com/NASA-PDS/registry/releases/
Author: PDS
Author-email: pds_operator@jpl.nasa.gov
License: apache-2.0
Keywords: pds,planetary data,registry
Classifier: Programming Language :: Python :: 3
Classifier: Programming Language :: Python :: 3.9
Classifier: License :: OSI Approved :: Apache Software License
Classifier: Operating System :: OS Independent
Requires-Python: >=3.9
License-File: LICENSE.md
License-File: NOTICE.txt
Requires-Dist: requests==2.32.3
Requires-Dist: Jinja2==3.1.4
Provides-Extra: dev
Requires-Dist: black~=23.7.0; extra == "dev"
Requires-Dist: docutils==0.16; extra == "dev"
Requires-Dist: flake8~=6.1.0; extra == "dev"
Requires-Dist: flake8-bugbear~=23.7.10; extra == "dev"
Requires-Dist: flake8-docstrings~=1.7.0; extra == "dev"
Requires-Dist: Jinja2==3.1.4; extra == "dev"
Requires-Dist: pep8-naming~=0.13.3; extra == "dev"
Requires-Dist: mypy~=1.5.1; extra == "dev"
Requires-Dist: pydocstyle~=6.3.0; extra == "dev"
Requires-Dist: coverage~=7.3.0; extra == "dev"
Requires-Dist: pytest~=7.4.0; extra == "dev"
Requires-Dist: pytest-cov~=4.1.0; extra == "dev"
Requires-Dist: pytest-watch~=4.2.0; extra == "dev"
Requires-Dist: pytest-xdist~=3.3.1; extra == "dev"
Requires-Dist: pre-commit~=3.3.3; extra == "dev"
Requires-Dist: sphinx~=5.3.0; extra == "dev"
Requires-Dist: sphinx-rtd-theme~=0.5.0; extra == "dev"
Requires-Dist: sphinxcontrib-openapi~=0.8.4; extra == "dev"
Requires-Dist: sphinxcontrib-redoc~=1.6.0; extra == "dev"
Requires-Dist: tox~=4.11.0; extra == "dev"
Requires-Dist: types-setuptools~=68.1.0.0; extra == "dev"
Requires-Dist: types-requests==2.32.0.20250328; extra == "dev"
Requires-Dist: types-pkg_resources==0.1.3; extra == "dev"
Dynamic: download-url
Dynamic: license-file
